fptk/__init__.py
fptk/async_tools.py
fptk/validate.py
fptk/adt/__init__.py
fptk/adt/nelist.py
fptk/adt/option.py
fptk/adt/reader.py
fptk/adt/result.py
fptk/adt/state.py
fptk/adt/traverse.py
fptk/adt/writer.py
fptk/core/__init__.py
fptk/core/func.py
fptk/iter/__init__.py
fptk/iter/lazy.py
fptk-1.2.0.dist-info/METADATA
fptk-1.2.0.dist-info/WHEEL
fptk-1.2.0.dist-info/licenses/LICENSE
fptk-1.2.0.dist-info/RECORD
