Metadata-Version: 2.4
Name: fptk
Version: 1.2.0
Summary: Pragmatic functional programming library for Python.
Project-URL: Homepage, https://github.com/mhbxyz/fptk
Project-URL: Documentation, https://mhbxyz.github.io/fptk
Project-URL: Issues, https://github.com/mhbxyz/fptk/issues
Author-email: Manoah BERNIER <manoah.bernier@gmail.com>
License: MIT
License-File: LICENSE
Keywords: compose,functional,iterators,monad,option,pipe,result
Classifier: Intended Audience :: Developers
Classifier: License :: OSI Approved :: MIT License
Classifier: Programming Language :: Python
Classifier: Programming Language :: Python :: 3
Classifier: Programming Language :: Python :: 3 :: Only
Classifier: Programming Language :: Python :: 3.13
Classifier: Topic :: Software Development :: Libraries
Classifier: Typing :: Typed
Requires-Python: >=3.13
